uop_mcp_server/__init__.py
uop_mcp_server/client.py
uop_mcp_server-2.0.5.dist-info/METADATA
uop_mcp_server-2.0.5.dist-info/WHEEL
uop_mcp_server-2.0.5.dist-info/RECORD
