Metadata-Version: 2.4
Name: uop_mcp_server
Version: 2.0.5
Summary: Universal MCP Server for AI-powered e-commerce integration via HTTP API
Project-URL: Homepage, https://unifiedoffer.com/mcp
Project-URL: Documentation, https://unifiedoffer.com/docs
Project-URL: Repository, https://github.com/Chris85appding/unified-offer-protocol-front
Project-URL: Issues, https://github.com/Chris85appding/unified-offer-protocol-front/issues
Author-email: Unified Offer Protocol <support@unifiedoffer.com>
License: MIT
Keywords: affiliate,ai,assistant,e-commerce,mcp,model-context-protocol,price-negotiation,product-search,shopify,shopware,woocommerce
Classifier: Development Status :: 5 - Production/Stable
Classifier: Intended Audience :: Developers
Classifier: License :: OSI Approved :: MIT License
Classifier: Programming Language :: Python :: 3
Classifier: Programming Language :: Python :: 3.8
Classifier: Programming Language :: Python :: 3.9
Classifier: Programming Language :: Python :: 3.10
Classifier: Programming Language :: Python :: 3.11
Classifier: Programming Language :: Python :: 3.12
Classifier: Topic :: Software Development :: Libraries :: Python Modules
Requires-Python: >=3.8
Requires-Dist: httpx>=0.24.0
Requires-Dist: pydantic>=2.0.0
